pyavatar/__init__.py
pyavatar/_version.py
pyavatar/font/Lora.ttf
pyavatar-0.1.8.dist-info/licenses/LICENSE
pyavatar-0.1.8.dist-info/METADATA
pyavatar-0.1.8.dist-info/WHEEL
pyavatar-0.1.8.dist-info/top_level.txt
pyavatar-0.1.8.dist-info/RECORD
