Metadata-Version: 2.4
Name: pyavatar
Version: 0.1.8
Summary: Generate simple user avatars from an input string.
Home-page: https://github.com/smallwat3r/pyavatar
Author: Matthieu Petiteau
Author-email: mpetiteau.pro@gmail.com
License: MIT
Keywords: avatar
Classifier: Programming Language :: Python :: 3
Classifier: Programming Language :: Python :: 3.10
Classifier: Programming Language :: Python :: 3.11
Classifier: License :: OSI Approved :: MIT License
Classifier: Operating System :: OS Independent
Requires-Python: >=3.10
License-File: LICENSE
Requires-Dist: Pillow>10
Dynamic: author
Dynamic: author-email
Dynamic: classifier
Dynamic: description
Dynamic: description-content-type
Dynamic: home-page
Dynamic: keywords
Dynamic: license
Dynamic: license-file
Dynamic: requires-dist
Dynamic: requires-python
Dynamic: summary
